fissionmunk/__init__.py
fissionmunk/ControlRod.py
fissionmunk/Core.py
fissionmunk/Fuel.py
fissionmunk/FuelElement.py
fissionmunk/helper.py
fissionmunk/Material.py
fissionmunk/mechanics.py
fissionmunk/Moderator.py
fissionmunk/Neutron.py
fissionmunk/Water.py
fissionmunk-0.0.5.dist-info/licenses/LICENSE
fissionmunk-0.0.5.dist-info/METADATA
fissionmunk-0.0.5.dist-info/WHEEL
fissionmunk-0.0.5.dist-info/RECORD
