Metadata-Version: 2.4
Name: fissionmunk
Version: 0.0.5
Summary: FissionMunk is a lightweight 2D physics open source python library designed to simulate nuclear fission reactor mechanics.
License: MIT
License-File: LICENSE
Keywords: fission,nuclear,physics,simulation,reactor,2D,python,library,open-source,pymunk,ianiket23
Author: Aniket Mishra
Author-email: ianiket23@gmail.com
Requires-Python: >=3.6
Classifier: License :: OSI Approved :: MIT License
Classifier: Programming Language :: Python :: 3
Classifier: Programming Language :: Python :: 3.6
Classifier: Programming Language :: Python :: 3.7
Classifier: Programming Language :: Python :: 3.8
Classifier: Programming Language :: Python :: 3.9
Classifier: Programming Language :: Python :: 3.10
Classifier: Programming Language :: Python :: 3.11
Classifier: Programming Language :: Python :: 3.12
Classifier: Programming Language :: Python :: 3.13
Classifier: Programming Language :: Python :: 3.14
Requires-Dist: pymunk (==6.9.0)
Project-URL: Homepage, https://github.com/iAniket23/fissionmunk
Project-URL: Repository, https://github.com/iAniket23/fissionmunk
